anarci/__init__.py
anarci/anarci/__init__.py
anarci/anarci/anarci.py
anarci/anarci/constants.py
anarci/anarci/schemes.py
anarci/anarci/utils.py
anarci/build_models/__init__.py
anarci/build_models/build_models.py
anarci/build_models/download_data.py
anarci/build_models/fasta_parser.py
anarci/build_models/format_alignments.py
anarci/build_models/parse_mhc_data.py
anarci/dat/HMMs/ALL.hmm
anarci/dat/HMMs/ALL.hmm.h3f
anarci/dat/HMMs/ALL.hmm.h3i
anarci/dat/HMMs/ALL.hmm.h3m
anarci/dat/HMMs/ALL.hmm.h3p
anarci_mhc-0.0.13.data/data/bin/ANARCI
anarci_mhc-0.0.13.data/data/bin/muscle
anarci_mhc-0.0.13.data/data/bin/muscle_macOS
anarci_mhc-0.0.13.data/scripts/ANARCI
anarci_mhc-0.0.13.dist-info/licenses/LICENCE
anarci_mhc-0.0.13.dist-info/licenses/LICENCE_MUSCLE
test_anarci/__init__.py
test_anarci/test_anarci_edge_cases.py
test_anarci/test_anarci_output.py
test_anarci/test_anarci_python_api.py
anarci_mhc-0.0.13.dist-info/METADATA
anarci_mhc-0.0.13.dist-info/WHEEL
anarci_mhc-0.0.13.dist-info/top_level.txt
anarci_mhc-0.0.13.dist-info/RECORD
